netbox_svm/__init__.py
netbox_svm/admin.py
netbox_svm/filtersets.py
netbox_svm/navigation.py
netbox_svm/search.py
netbox_svm/tables.py
netbox_svm/template_content.py
netbox_svm/urls.py
netbox_svm/api/__init__.py
netbox_svm/api/serializers.py
netbox_svm/api/urls.py
netbox_svm/api/views.py
netbox_svm/forms/__init__.py
netbox_svm/forms/software_license.py
netbox_svm/forms/software_product.py
netbox_svm/forms/software_product_installation.py
netbox_svm/forms/software_product_version.py
netbox_svm/forms/software_version_install_remove.py
netbox_svm/migrations/0001_initial.py
netbox_svm/migrations/__init__.py
netbox_svm/models/__init__.py
netbox_svm/models/softwarelicense.py
netbox_svm/models/softwareproduct.py
netbox_svm/models/softwareproductinstallation.py
netbox_svm/models/softwareproductversion.py
netbox_svm/templates/netbox_svm/softwarelicense.html
netbox_svm/templates/netbox_svm/softwareproduct.html
netbox_svm/templates/netbox_svm/softwareproductinstallation.html
netbox_svm/templates/netbox_svm/softwareproductversion.html
netbox_svm/templates/netbox_svm/generic/bulk_remove.html
netbox_svm/templates/netbox_svm/inc/software_version_info.html
netbox_svm/templates/netbox_svm/inc/softwareproductinstallation_button.html
netbox_svm/templates/viewtab_version/software_installations.html
netbox_svm/templates/viewtab_version/software_installations_base.html
netbox_svm/templatetags/__init__.py
netbox_svm/views/__init__.py
netbox_svm/views/software_license.py
netbox_svm/views/software_product.py
netbox_svm/views/software_product_installation.py
netbox_svm/views/software_product_version.py
netbox_svm/views/version_viewtab_software_installation.py
netbox_svm/views/version_viewtab_software_license.py
netbox_svm-1.1.7.dist-info/LICENSE
netbox_svm-1.1.7.dist-info/METADATA
netbox_svm-1.1.7.dist-info/WHEEL
netbox_svm-1.1.7.dist-info/top_level.txt
netbox_svm-1.1.7.dist-info/RECORD
